jgrapht/__init__.py
jgrapht/__version__.py
jgrapht/_backend.cpython-37m-x86_64-linux-gnu.so
jgrapht/backend.py
jgrapht/convert.py
jgrapht/generators.py
jgrapht/libjgrapht_capi.so
jgrapht/metrics.py
jgrapht/properties.py
jgrapht/traversal.py
jgrapht/types.py
jgrapht/utils.py
jgrapht/views.py
jgrapht/_internals/__init__.py
jgrapht/_internals/_anyhashableg.py
jgrapht/_internals/_anyhashableg_clustering.py
jgrapht/_internals/_anyhashableg_collections.py
jgrapht/_internals/_anyhashableg_drawing.py
jgrapht/_internals/_anyhashableg_flows.py
jgrapht/_internals/_anyhashableg_mapping.py
jgrapht/_internals/_anyhashableg_paths.py
jgrapht/_internals/_anyhashableg_planar.py
jgrapht/_internals/_anyhashableg_wrappers.py
jgrapht/_internals/_attributes.py
jgrapht/_internals/_callbacks.py
jgrapht/_internals/_clustering.py
jgrapht/_internals/_collections.py
jgrapht/_internals/_drawing.py
jgrapht/_internals/_flows.py
jgrapht/_internals/_graphs.py
jgrapht/_internals/_importers.py
jgrapht/_internals/_ioutils.py
jgrapht/_internals/_mapping.py
jgrapht/_internals/_paths.py
jgrapht/_internals/_planar.py
jgrapht/_internals/_views.py
jgrapht/_internals/_wrappers.py
jgrapht/algorithms/__init__.py
jgrapht/algorithms/cliques.py
jgrapht/algorithms/clustering.py
jgrapht/algorithms/coloring.py
jgrapht/algorithms/connectivity.py
jgrapht/algorithms/cuts.py
jgrapht/algorithms/cycles.py
jgrapht/algorithms/drawing.py
jgrapht/algorithms/flow.py
jgrapht/algorithms/independent.py
jgrapht/algorithms/isomorphism.py
jgrapht/algorithms/matching.py
jgrapht/algorithms/partition.py
jgrapht/algorithms/planar.py
jgrapht/algorithms/scoring.py
jgrapht/algorithms/shortestpaths.py
jgrapht/algorithms/spanning.py
jgrapht/algorithms/tour.py
jgrapht/algorithms/vertexcover.py
jgrapht/drawing/__init__.py
jgrapht/drawing/draw_matplotlib.py
jgrapht/io/__init__.py
jgrapht/io/edgelist.py
jgrapht/io/exporters.py
jgrapht/io/importers.py
jgrapht-1.5.0.3.dist-info/METADATA
jgrapht-1.5.0.3.dist-info/WHEEL
jgrapht-1.5.0.3.dist-info/top_level.txt
jgrapht-1.5.0.3.dist-info/RECORD
